LICENSE
MANIFEST.in
README.MD
setup.py
pybotman/__init__.py
pybotman/client.py
pybotman.egg-info/PKG-INFO
pybotman.egg-info/SOURCES.txt
pybotman.egg-info/dependency_links.txt
pybotman.egg-info/requires.txt
pybotman.egg-info/top_level.txt