Metadata-Version: 2.1
Name: pybotman
Version: 1.0.3
Summary: Python API wrapper for botman bots
Home-page: https://github.com/Flowelcat/pybotman
Author: Flowelcat
Author-email: flowelcat@gmail.com
License: apache-2.0
Download-URL: https://github.com/Flowelcat/pybotman/archive/v.1.0.3.tar.gz
Keywords: botman,pybotman,botmanbot,botmanapi
Platform: UNKNOWN
Classifier: Development Status :: 4 - Beta
Classifier: Intended Audience :: Developers
Classifier: Topic :: Software Development :: Libraries :: Python Modules
Classifier: License :: OSI Approved :: Apache Software License
Classifier: Programming Language :: Python :: 3
Classifier: Programming Language :: Python :: 3.4
Classifier: Programming Language :: Python :: 3.5
Classifier: Programming Language :: Python :: 3.6
Requires-Python: >3.6.0
